DefaultCreds/DefaultCreds_db.json
DefaultCreds/__init__.py
DefaultCreds/creds.py
defaultcreds_cheat_sheet-0.5.3.0.dist-info/LICENSE
defaultcreds_cheat_sheet-0.5.3.0.dist-info/METADATA
defaultcreds_cheat_sheet-0.5.3.0.dist-info/WHEEL
defaultcreds_cheat_sheet-0.5.3.0.dist-info/entry_points.txt
defaultcreds_cheat_sheet-0.5.3.0.dist-info/RECORD
