Metadata-Version: 2.3
Name: DefaultCreds_cheat_sheet
Version: 0.5.3.0
Summary: One place for all the default credentials to assist pentesters during an engagement, this document has several products default login/password gathered from multiple sources.
Author: ihebski
Author-email: botsy.project@gmail.com
Requires-Python: >=3.7.0,<4.0.0
Classifier: Environment :: Console
Classifier: License :: OSI Approved :: BSD License
Classifier: Programming Language :: Python :: 3
Classifier: Programming Language :: Python :: 3.7
Classifier: Programming Language :: Python :: 3.8
Classifier: Programming Language :: Python :: 3.9
Classifier: Programming Language :: Python :: 3.10
Classifier: Programming Language :: Python :: 3.11
Classifier: Programming Language :: Python :: 3.12
Classifier: Programming Language :: Python :: 3.13
Classifier: Topic :: Security
Requires-Dist: fire (>=0.5)
Requires-Dist: prettytable (>=3.6.0)
Requires-Dist: requests (>=2.28.2)
Requires-Dist: tinydb (>=4.7.1)
Project-URL: Homepage, https://github.com/ihebski/DefaultCreds-cheat-sheet
Project-URL: Repository, https://github.com/ihebski/DefaultCreds-cheat-sheet/issues
